flowrep/__init__.py
flowrep/_version.py
flowrep/model.py
flowrep/parser.py
flowrep/tools.py
flowrep/workflow.py
flowrep-0.1.9.dist-info/METADATA
flowrep-0.1.9.dist-info/WHEEL
flowrep-0.1.9.dist-info/licenses/LICENSE
flowrep-0.1.9.dist-info/RECORD
