Metadata-Version: 2.4
Name: flowrep
Version: 0.1.9
Summary: flowrep - Your premier tool for workflow representations
Project-URL: Homepage, https://pyiron.org/
Project-URL: Documentation, https://flowrep.readthedocs.io
Project-URL: Repository, https://github.com/pyiron/flowrep
Author-email: Sam Waseda <waseda@mpie.de>
License: BSD 3-Clause License
License-File: LICENSE
Keywords: pyiron
Classifier: Development Status :: 3 - Alpha
Classifier: Intended Audience :: Science/Research
Classifier: License :: OSI Approved :: BSD License
Classifier: Operating System :: OS Independent
Classifier: Programming Language :: Python :: 3.11
Classifier: Programming Language :: Python :: 3.12
Classifier: Programming Language :: Python :: 3.13
Classifier: Topic :: Scientific/Engineering
Requires-Python: <3.14,>=3.11
Requires-Dist: networkx<3.7.0,>=3.4.2
Requires-Dist: pydantic<2.13.0,>=2.12.0
